{
    "actor/character talk": {
        "able": 1,
        "absolutely": 1,
        "action": 1,
        "actually": 1,
        "ago": 3,
        "america": 1,
        "amp": 2,
        "asian": 2,
        "avengers": 2,
        "bad": 2,
        "bc": 1,
        "beautiful": 1,
        "believe": 1,
        "bit": 2,
        "black": 4,
        "brother": 2,
        "bus": 1,
        "captain": 1,
        "cast": 3,
        "character": 11,
        "comic": 1,
        "comics": 2,
        "coming": 2,
        "dad": 5,
        "damn": 1,
        "day": 1,
        "definitely": 1,
        "disney": 3,
        "doing": 1,
        "dr": 1,
        "dragon": 1,
        "eternals": 3,
        "exclusive": 1,
        "falcon": 1,
        "fantastic": 1,
        "favorite": 1,
        "feel": 2,
        "feels": 1,
        "films": 1,
        "finally": 2,
        "finished": 1,
        "free": 1,
        "friends": 2,
        "fun": 3,
        "funko": 4,
        "funny": 1,
        "future": 1,
        "getting": 2,
        "girl": 1,
        "god": 2,
        "gonna": 1,
        "gt": 3,
        "guy": 3,
        "happy": 2,
        "heard": 1,
        "heart": 1,
        "hell": 1,
        "help": 3,
        "hit": 1,
        "home": 1,
        "hoping": 1,
        "https": 30,
        "idea": 1,
        "idk": 1,
        "iron": 1,
        "katy": 4,
        "legend": 3,
        "leung": 1,
        "life": 1,
        "liked": 2,
        "little": 1,
        "liu": 6,
        "lol": 1,
        "looking": 1,
        "looks": 3,
        "lot": 1,
        "love": 2,
        "loved": 3,
        "lt": 1,
        "makes": 1,
        "marvel": 10,
        "maybe": 1,
        "mcu": 4,
        "minutes": 2,
        "mom": 2,
        "movie": 10,
        "movies": 1,
        "notice": 1,
        "oh": 3,
        "ok": 1,
        "okay": 2,
        "omg": 1,
        "panther": 2,
        "people": 3,
        "phase": 2,
        "please": 1,
        "pop": 1,
        "post": 1,
        "power": 1,
        "pre": 1,
        "pretty": 3,
        "real": 1,
        "rings": 5,
        "rt": 1,
        "saying": 2,
        "scene": 1,
        "screen": 2,
        "seeing": 2,
        "seen": 2,
        "set": 3,
        "shit": 3,
        "simu": 6,
        "sister": 2,
        "soldier": 1,
        "solid": 2,
        "soon": 1,
        "spider": 2,
        "story": 1,
        "strange": 2,
        "stuff": 1,
        "team": 1,
        "tell": 2,
        "ten": 4,
        "thinking": 2,
        "time": 4,
        "tonight": 1,
        "tony": 1,
        "totally": 1,
        "trying": 1,
        "villain": 2,
        "wait": 1,
        "wanda": 1,
        "wanna": 2,
        "watch": 3,
        "watched": 5,
        "watching": 6,
        "weeks": 1,
        "wenwu": 2,
        "widow": 1,
        "winter": 2,
        "wong": 3,
        "xialing": 11,
        "xu": 4,
        "ya": 1
    },
    "advertisement": {
        "actually": 1,
        "ad": 11,
        "am": 1,
        "amp": 7,
        "black": 2,
        "blu": 12,
        "bluemiracle": 1,
        "buy": 3,
        "cause": 2,
        "cinema": 1,
        "comes": 1,
        "coming": 1,
        "copy": 9,
        "day": 1,
        "deleted": 4,
        "die": 10,
        "digital": 5,
        "disney": 11,
        "doing": 1,
        "doompatrol": 1,
        "dracula": 1,
        "dune": 1,
        "enjoy": 1,
        "eternals": 3,
        "exclusive": 9,
        "experience": 4,
        "falcon": 1,
        "feel": 1,
        "fight": 2,
        "film": 1,
        "films": 1,
        "free": 3,
        "funko": 3,
        "giveaway": 10,
        "goes": 1,
        "gone": 1,
        "guy": 1,
        "happy": 1,
        "hawkeye": 1,
        "hbomax": 1,
        "hd": 12,
        "hit": 10,
        "home": 11,
        "https": 71,
        "hustle": 10,
        "johnleguizamoslatinhistoryformorons": 1,
        "join": 12,
        "kong": 1,
        "late": 2,
        "legend": 41,
        "life": 2,
        "listen": 1,
        "loki": 1,
        "luisesparza": 1,
        "maid": 1,
        "marvel": 27,
        "marvelstudios": 12,
        "mcu": 10,
        "midnightmass": 1,
        "miss": 2,
        "movie": 14,
        "movies": 13,
        "netflix": 2,
        "night": 1,
        "notice": 11,
        "november": 1,
        "pablo": 1,
        "please": 1,
        "pop": 3,
        "pre": 7,
        "ray": 12,
        "ready": 2,
        "real": 2,
        "red": 11,
        "release": 1,
        "retweet": 2,
        "review": 1,
        "reviewed": 1,
        "rings": 38,
        "rt": 1,
        "scenes": 8,
        "seeing": 1,
        "seen": 1,
        "share": 1,
        "soldier": 1,
        "spiderman": 10,
        "start": 1,
        "starwars": 1,
        "stores": 7,
        "sweepstakes": 11,
        "swvisions": 1,
        "talkingnerdy": 1,
        "talknerdytome": 1,
        "team": 1,
        "ten": 41,
        "theambassador": 1,
        "theater": 2,
        "tickets": 1,
        "time": 11,
        "tomorrow": 6,
        "tuesday": 7,
        "venom": 10,
        "via": 10,
        "vs": 1,
        "walmart": 5,
        "wandavision": 1,
        "watch": 4,
        "week": 3,
        "weekly": 1,
        "wenwu": 2,
        "widow": 2,
        "win": 2,
        "winter": 1,
        "xu": 1
    },
    "comparison": {
        "action": 3,
        "actually": 13,
        "amp": 12,
        "avengers": 3,
        "awesome": 2,
        "bad": 2,
        "bc": 1,
        "bit": 2,
        "black": 23,
        "cgi": 1,
        "character": 1,
        "choreography": 1,
        "cinema": 2,
        "civil": 2,
        "comes": 1,
        "comic": 1,
        "comics": 1,
        "coming": 1,
        "day": 1,
        "definitely": 2,
        "die": 1,
        "disney": 2,
        "doing": 1,
        "dr": 1,
        "dune": 5,
        "endgame": 6,
        "enjoyed": 1,
        "enjoying": 1,
        "eternals": 29,
        "eyes": 2,
        "falcon": 14,
        "fantastic": 1,
        "favorite": 2,
        "feel": 11,
        "feels": 2,
        "fight": 4,
        "film": 2,
        "films": 4,
        "finally": 1,
        "fine": 1,
        "finished": 1,
        "free": 12,
        "fun": 1,
        "funny": 1,
        "future": 1,
        "god": 1,
        "goes": 1,
        "gonna": 4,
        "gt": 19,
        "guy": 1,
        "half": 1,
        "happened": 1,
        "hawkeye": 5,
        "home": 9,
        "honestly": 2,
        "https": 25,
        "hustle": 1,
        "idea": 1,
        "im": 1,
        "imax": 2,
        "infinity": 2,
        "iron": 4,
        "kong": 3,
        "late": 1,
        "legend": 8,
        "leung": 1,
        "liked": 1,
        "list": 4,
        "loki": 13,
        "lol": 3,
        "looking": 1,
        "lot": 2,
        "love": 1,
        "loved": 1,
        "makes": 2,
        "marvel": 13,
        "marvelstudios": 2,
        "maybe": 1,
        "mcu": 14,
        "minutes": 1,
        "movie": 11,
        "movies": 13,
        "notice": 1,
        "november": 1,
        "ok": 1,
        "okay": 4,
        "omg": 1,
        "panther": 5,
        "people": 3,
        "phase": 4,
        "please": 1,
        "post": 1,
        "probably": 4,
        "ready": 1,
        "red": 1,
        "release": 1,
        "reviewed": 11,
        "rings": 6,
        "saying": 3,
        "scene": 1,
        "scenes": 1,
        "screen": 1,
        "seeing": 1,
        "seen": 3,
        "series": 1,
        "set": 2,
        "share": 10,
        "shit": 2,
        "short": 1,
        "sm": 1,
        "soldier": 14,
        "soon": 2,
        "soundtrack": 1,
        "spider": 12,
        "spiderman": 3,
        "start": 2,
        "strange": 3,
        "stuff": 3,
        "suicide": 1,
        "super": 1,
        "tell": 1,
        "ten": 7,
        "tho": 1,
        "time": 4,
        "times": 1,
        "tony": 1,
        "top": 4,
        "venom": 7,
        "villain": 1,
        "vs": 4,
        "wandavision": 12,
        "wanna": 1,
        "war": 3,
        "watch": 2,
        "watched": 3,
        "watching": 3,
        "week": 1,
        "weekend": 1,
        "weekly": 11,
        "widow": 18,
        "winter": 16,
        "wish": 1,
        "ya": 1
    },
    "release": {
        "able": 2,
        "actually": 1,
        "ago": 1,
        "am": 1,
        "america": 1,
        "amp": 2,
        "asian": 2,
        "ass": 1,
        "avengers": 1,
        "believe": 1,
        "black": 4,
        "blu": 5,
        "china": 1,
        "comes": 1,
        "comics": 1,
        "cool": 1,
        "damn": 1,
        "day": 4,
        "die": 1,
        "dir": 4,
        "disney": 5,
        "dune": 1,
        "eternals": 6,
        "experience": 1,
        "favorite": 1,
        "films": 1,
        "finally": 2,
        "fucking": 2,
        "getting": 1,
        "god": 1,
        "gone": 1,
        "happy": 1,
        "heard": 1,
        "hit": 1,
        "home": 3,
        "honestly": 1,
        "hoping": 2,
        "https": 11,
        "idk": 1,
        "legend": 3,
        "liu": 1,
        "lol": 1,
        "marvel": 6,
        "maybe": 1,
        "mcu": 1,
        "movie": 10,
        "movies": 3,
        "night": 1,
        "november": 2,
        "panther": 1,
        "people": 1,
        "perfect": 1,
        "phase": 1,
        "please": 2,
        "post": 1,
        "pretty": 1,
        "quality": 1,
        "ray": 4,
        "release": 5,
        "rings": 2,
        "saying": 1,
        "scene": 1,
        "screen": 1,
        "set": 1,
        "shit": 1,
        "simu": 1,
        "soon": 1,
        "spider": 4,
        "story": 1,
        "suicide": 1,
        "team": 1,
        "ten": 4,
        "thank": 1,
        "theater": 3,
        "tho": 2,
        "tickets": 2,
        "time": 4,
        "times": 2,
        "tomorrow": 1,
        "wait": 3,
        "watch": 2,
        "watched": 1,
        "week": 3,
        "weeks": 2,
        "widow": 4,
        "wish": 1
    },
    "review": {
        "able": 1,
        "absolutely": 2,
        "action": 7,
        "actually": 3,
        "ad": 2,
        "am": 2,
        "amazing": 9,
        "america": 1,
        "amp": 11,
        "asian": 4,
        "ass": 4,
        "avengers": 1,
        "awesome": 1,
        "bad": 4,
        "bc": 2,
        "beautiful": 5,
        "bit": 3,
        "black": 11,
        "bro": 1,
        "brother": 1,
        "buy": 3,
        "captain": 1,
        "cast": 2,
        "cgi": 2,
        "character": 1,
        "chinese": 3,
        "choreography": 3,
        "civil": 1,
        "comic": 3,
        "comics": 1,
        "cool": 3,
        "dad": 1,
        "damn": 5,
        "day": 2,
        "definitely": 2,
        "die": 2,
        "disney": 3,
        "doing": 1,
        "dragon": 1,
        "dude": 2,
        "dune": 2,
        "endgame": 2,
        "enjoyed": 7,
        "eternals": 9,
        "excited": 2,
        "eyes": 2,
        "falcon": 1,
        "fantastic": 3,
        "father": 1,
        "favorite": 4,
        "feel": 3,
        "feels": 3,
        "fight": 8,
        "film": 11,
        "films": 5,
        "finally": 16,
        "fine": 3,
        "finished": 2,
        "free": 4,
        "fuck": 1,
        "fucking": 3,
        "fun": 6,
        "funko": 2,
        "future": 2,
        "giveaway": 2,
        "god": 2,
        "goes": 1,
        "guy": 4,
        "half": 1,
        "happy": 1,
        "hawkeye": 2,
        "heard": 1,
        "heart": 1,
        "hell": 1,
        "help": 1,
        "hit": 1,
        "home": 1,
        "honestly": 2,
        "https": 45,
        "idea": 1,
        "idk": 4,
        "infinity": 2,
        "iron": 1,
        "katy": 1,
        "late": 6,
        "legend": 29,
        "leung": 1,
        "liked": 4,
        "list": 1,
        "little": 2,
        "liu": 1,
        "loki": 2,
        "lol": 2,
        "looking": 4,
        "looks": 1,
        "lot": 5,
        "love": 8,
        "loved": 6,
        "makes": 3,
        "marvel": 30,
        "marvelstudios": 5,
        "maybe": 1,
        "mcu": 14,
        "mean": 3,
        "mom": 1,
        "movie": 45,
        "movies": 14,
        "night": 3,
        "notice": 1,
        "oh": 1,
        "ok": 2,
        "okay": 5,
        "omg": 1,
        "panther": 2,
        "people": 3,
        "perfect": 2,
        "phase": 3,
        "please": 1,
        "pop": 1,
        "power": 1,
        "pretty": 5,
        "probably": 3,
        "quality": 3,
        "real": 1,
        "red": 3,
        "release": 2,
        "review": 8,
        "rings": 36,
        "saying": 1,
        "scene": 1,
        "scenes": 6,
        "seeing": 3,
        "seen": 5,
        "series": 2,
        "shit": 4,
        "short": 2,
        "simu": 1,
        "sm": 2,
        "soldier": 2,
        "solid": 3,
        "soundtrack": 1,
        "spider": 1,
        "spiderman": 3,
        "start": 1,
        "story": 7,
        "strange": 1,
        "stuff": 2,
        "suicide": 1,
        "super": 2,
        "sweepstakes": 2,
        "tell": 2,
        "ten": 30,
        "thank": 2,
        "theater": 1,
        "tho": 2,
        "till": 1,
        "time": 5,
        "tomorrow": 3,
        "tonight": 1,
        "tony": 1,
        "top": 9,
        "totally": 2,
        "trying": 1,
        "venom": 1,
        "via": 3,
        "villain": 1,
        "wait": 2,
        "wandavision": 2,
        "wanna": 1,
        "war": 1,
        "watch": 5,
        "watched": 11,
        "watching": 5,
        "week": 1,
        "weekend": 1,
        "wenwu": 1,
        "widow": 8,
        "win": 1,
        "winter": 2,
        "wish": 3,
        "wow": 3,
        "xialing": 2,
        "xu": 2,
        "ya": 3,
        "yeah": 3
    },
    "scene/plot talk": {
        "abt": 3,
        "action": 4,
        "actually": 1,
        "am": 1,
        "amazing": 1,
        "asian": 6,
        "ass": 1,
        "avengers": 3,
        "bc": 1,
        "believe": 2,
        "bit": 1,
        "black": 2,
        "bus": 9,
        "captain": 2,
        "cause": 1,
        "cgi": 1,
        "china": 3,
        "cinema": 1,
        "comic": 1,
        "comics": 1,
        "coming": 2,
        "cool": 1,
        "dad": 3,
        "damn": 1,
        "day": 3,
        "definitely": 2,
        "deleted": 3,
        "die": 2,
        "disney": 3,
        "doing": 4,
        "dr": 1,
        "dragon": 3,
        "dragons": 3,
        "dune": 1,
        "endgame": 1,
        "enjoying": 1,
        "eternals": 3,
        "father": 1,
        "feels": 1,
        "fight": 11,
        "film": 6,
        "finally": 1,
        "friends": 1,
        "fucking": 4,
        "funny": 2,
        "future": 1,
        "getting": 2,
        "god": 1,
        "goes": 1,
        "gone": 1,
        "gonna": 2,
        "happened": 2,
        "hd": 1,
        "heard": 1,
        "heart": 1,
        "hell": 2,
        "hit": 1,
        "honestly": 1,
        "hoping": 1,
        "https": 26,
        "idea": 1,
        "im": 2,
        "instead": 2,
        "katy": 1,
        "kong": 1,
        "legend": 7,
        "life": 5,
        "liked": 1,
        "little": 2,
        "lol": 2,
        "lot": 2,
        "love": 8,
        "marvel": 9,
        "mcu": 7,
        "minutes": 1,
        "mom": 1,
        "movie": 10,
        "movies": 8,
        "night": 1,
        "oh": 1,
        "okay": 1,
        "perfect": 1,
        "please": 2,
        "power": 1,
        "pretty": 3,
        "probably": 1,
        "quality": 2,
        "review": 1,
        "rings": 11,
        "saying": 1,
        "scene": 16,
        "scenes": 7,
        "seeing": 3,
        "seen": 1,
        "series": 1,
        "share": 1,
        "shit": 4,
        "short": 1,
        "sister": 1,
        "sm": 1,
        "solid": 1,
        "soon": 1,
        "soundtrack": 1,
        "spider": 1,
        "start": 1,
        "story": 2,
        "strange": 2,
        "stuff": 4,
        "suicide": 1,
        "team": 1,
        "ten": 10,
        "thank": 2,
        "thinking": 3,
        "tho": 4,
        "time": 1,
        "top": 2,
        "totally": 1,
        "trying": 1,
        "venom": 2,
        "villain": 1,
        "vs": 1,
        "wait": 1,
        "wanda": 3,
        "war": 2,
        "watched": 7,
        "watching": 2,
        "week": 1,
        "wenwu": 1,
        "widow": 3,
        "wong": 2,
        "wow": 2,
        "xialing": 1,
        "yeah": 2
    },
    "too little info": {
        "able": 2,
        "absolutely": 1,
        "abt": 2,
        "actually": 1,
        "ad": 5,
        "am": 3,
        "amazing": 1,
        "america": 3,
        "amp": 15,
        "asian": 1,
        "ass": 2,
        "avengers": 3,
        "bad": 2,
        "bc": 1,
        "believe": 2,
        "bit": 1,
        "black": 5,
        "bluemiracle": 8,
        "bro": 1,
        "bus": 1,
        "buy": 1,
        "captain": 4,
        "cast": 1,
        "cause": 1,
        "cgi": 2,
        "china": 1,
        "chinese": 1,
        "choreography": 1,
        "civil": 2,
        "comic": 1,
        "comics": 1,
        "cool": 1,
        "dad": 2,
        "day": 2,
        "definitely": 1,
        "deleted": 2,
        "digital": 1,
        "dir": 1,
        "disney": 6,
        "doompatrol": 8,
        "dr": 2,
        "dracula": 8,
        "dragon": 1,
        "dragons": 1,
        "dude": 3,
        "endgame": 2,
        "enjoy": 2,
        "enjoying": 1,
        "eternals": 4,
        "excited": 1,
        "eyes": 1,
        "falcon": 1,
        "father": 3,
        "feel": 2,
        "film": 2,
        "films": 1,
        "fine": 2,
        "free": 4,
        "friends": 2,
        "fucking": 2,
        "fun": 1,
        "funny": 1,
        "getting": 1,
        "girl": 3,
        "giveaway": 4,
        "god": 1,
        "goes": 9,
        "gone": 1,
        "gonna": 3,
        "gt": 6,
        "guy": 2,
        "happened": 1,
        "happy": 1,
        "hawkeye": 3,
        "hbomax": 7,
        "heard": 2,
        "heart": 1,
        "hell": 2,
        "home": 2,
        "https": 101,
        "idk": 2,
        "im": 2,
        "instead": 2,
        "johnleguizamoslatinhistoryformorons": 8,
        "join": 2,
        "late": 1,
        "legend": 25,
        "liked": 2,
        "list": 1,
        "listen": 8,
        "little": 1,
        "loki": 3,
        "lol": 2,
        "looking": 1,
        "looks": 1,
        "lot": 1,
        "love": 5,
        "loved": 1,
        "lt": 3,
        "luisesparza": 8,
        "maid": 8,
        "makes": 2,
        "marvel": 16,
        "marvelstudios": 4,
        "maybe": 4,
        "mcu": 9,
        "mean": 2,
        "midnightmass": 8,
        "minutes": 1,
        "miss": 3,
        "mom": 2,
        "movie": 12,
        "movies": 3,
        "netflix": 8,
        "november": 1,
        "oh": 2,
        "ok": 3,
        "okay": 2,
        "omg": 1,
        "pablo": 8,
        "people": 2,
        "phase": 3,
        "please": 8,
        "post": 2,
        "power": 2,
        "pretty": 2,
        "probably": 1,
        "ready": 2,
        "real": 1,
        "retweet": 8,
        "review": 2,
        "rings": 27,
        "rt": 9,
        "saying": 1,
        "scene": 2,
        "seeing": 3,
        "series": 1,
        "shit": 2,
        "short": 1,
        "simu": 1,
        "sister": 2,
        "sm": 1,
        "soldier": 3,
        "spider": 1,
        "spiderman": 1,
        "start": 1,
        "starwars": 7,
        "strange": 1,
        "super": 1,
        "sweepstakes": 4,
        "swvisions": 7,
        "talkingnerdy": 7,
        "talknerdytome": 8,
        "team": 1,
        "tell": 2,
        "ten": 29,
        "thank": 1,
        "theambassador": 8,
        "theater": 3,
        "thinking": 1,
        "tickets": 1,
        "till": 1,
        "time": 1,
        "times": 1,
        "top": 1,
        "trying": 2,
        "tuesday": 1,
        "venom": 1,
        "via": 5,
        "villain": 1,
        "vs": 2,
        "walmart": 1,
        "wanda": 2,
        "wanna": 1,
        "war": 1,
        "watch": 7,
        "watching": 3,
        "week": 1,
        "weeks": 1,
        "wenwu": 1,
        "widow": 3,
        "winter": 2,
        "xu": 1,
        "yeah": 3,
        "yes": 5
    },
    "watching": {
        "able": 2,
        "absolutely": 1,
        "action": 1,
        "actually": 3,
        "ago": 1,
        "am": 1,
        "amazing": 4,
        "america": 1,
        "amp": 4,
        "asian": 1,
        "ass": 2,
        "avengers": 2,
        "awesome": 2,
        "bad": 2,
        "beautiful": 2,
        "black": 5,
        "blu": 1,
        "bro": 3,
        "brother": 2,
        "bus": 2,
        "buy": 2,
        "captain": 1,
        "cause": 1,
        "chinese": 1,
        "cinema": 3,
        "civil": 1,
        "comes": 3,
        "dad": 2,
        "damn": 1,
        "day": 5,
        "definitely": 2,
        "die": 1,
        "digital": 1,
        "disney": 1,
        "dragon": 1,
        "dragons": 1,
        "endgame": 1,
        "enjoy": 2,
        "enjoying": 2,
        "eternals": 7,
        "excited": 3,
        "falcon": 1,
        "favorite": 2,
        "fight": 1,
        "film": 5,
        "films": 1,
        "finally": 26,
        "finished": 9,
        "fuck": 8,
        "fucking": 2,
        "fun": 4,
        "funko": 1,
        "funny": 2,
        "getting": 2,
        "girl": 2,
        "god": 2,
        "gone": 1,
        "gonna": 4,
        "half": 3,
        "happened": 1,
        "happy": 2,
        "hawkeye": 2,
        "heard": 2,
        "heart": 1,
        "hell": 1,
        "help": 1,
        "home": 1,
        "honestly": 2,
        "hoping": 1,
        "https": 22,
        "idea": 1,
        "im": 5,
        "imax": 3,
        "infinity": 2,
        "instead": 2,
        "late": 2,
        "legend": 10,
        "leung": 2,
        "life": 1,
        "liked": 3,
        "list": 1,
        "listen": 1,
        "loki": 2,
        "lol": 3,
        "looking": 1,
        "lot": 3,
        "love": 3,
        "loved": 3,
        "lt": 1,
        "makes": 1,
        "marvel": 9,
        "marvelstudios": 1,
        "mcu": 4,
        "minutes": 1,
        "miss": 1,
        "mom": 1,
        "movie": 25,
        "movies": 6,
        "night": 8,
        "notice": 1,
        "okay": 1,
        "omg": 2,
        "panther": 2,
        "people": 3,
        "perfect": 1,
        "phase": 1,
        "pop": 1,
        "post": 1,
        "pretty": 2,
        "ray": 2,
        "red": 2,
        "release": 1,
        "review": 1,
        "rewatching": 6,
        "rings": 9,
        "saying": 1,
        "scene": 2,
        "screen": 5,
        "seeing": 2,
        "seen": 7,
        "series": 1,
        "shit": 2,
        "soldier": 1,
        "soon": 3,
        "soundtrack": 2,
        "spider": 3,
        "spiderman": 1,
        "stuff": 3,
        "suicide": 1,
        "super": 1,
        "ten": 8,
        "thank": 1,
        "thinking": 3,
        "tho": 1,
        "tickets": 3,
        "till": 3,
        "time": 16,
        "times": 3,
        "tomorrow": 2,
        "tonight": 3,
        "tony": 2,
        "totally": 1,
        "trying": 1,
        "wait": 1,
        "wandavision": 1,
        "wanna": 3,
        "war": 3,
        "watch": 26,
        "watched": 32,
        "watching": 37,
        "week": 1,
        "weekend": 3,
        "weeks": 3,
        "wenwu": 1,
        "widow": 3,
        "win": 2,
        "winter": 1,
        "wish": 4,
        "xialing": 1,
        "yes": 4
    }
}